{
  "__data_type": "DLG ",
  "DelayEntry": {
    "type": "dword",
    "value": 0
  },
  "DelayReply": {
    "type": "dword",
    "value": 0
  },
  "EndConverAbort": {
    "type": "resref",
    "value": "nw_walk_wp"
  },
  "EndConversation": {
    "type": "resref",
    "value": "nw_walk_wp"
  },
  "EntryList": {
    "type": "list",
    "value": [
      {
        "__struct_id": 0,
        "Animation": {
          "type": "dword",
          "value": 0
        },
        "AnimLoop": {
          "type": "byte",
          "value": 1
        },
        "Comment": {
          "type": "cexostring",
          "value": ""
        },
        "Delay": {
          "type": "dword",
          "value": 4294967295
        },
        "Quest": {
          "type": "cexostring",
          "value": ""
        },
        "RepliesList": {
          "type": "list",
          "value": [
            {
              "__struct_id": 0,
              "Active": {
                "type": "resref",
                "value": ""
              },
              "Index": {
                "type": "dword",
                "value": 0
              },
              "IsChild": {
                "type": "byte",
                "value": 0
              }
            }
          ]
        },
        "Script": {
          "type": "resref",
          "value": ""
        },
        "Sound": {
          "type": "resref",
          "value": ""
        },
        "Speaker": {
          "type": "cexostring",
          "value": ""
        },
        "Text": {
          "type": "cexolocstring",
          "value": {
            "0": "You seek out more knowledge on the Avatars?"
          }
        }
      },
      {
        "__struct_id": 1,
        "Animation": {
          "type": "dword",
          "value": 0
        },
        "AnimLoop": {
          "type": "byte",
          "value": 1
        },
        "Comment": {
          "type": "cexostring",
          "value": ""
        },
        "Delay": {
          "type": "dword",
          "value": 4294967295
        },
        "Quest": {
          "type": "cexostring",
          "value": ""
        },
        "RepliesList": {
          "type": "list",
          "value": [
            {
              "__struct_id": 0,
              "Active": {
                "type": "resref",
                "value": ""
              },
              "Index": {
                "type": "dword",
                "value": 1
              },
              "IsChild": {
                "type": "byte",
                "value": 0
              }
            }
          ]
        },
        "Script": {
          "type": "resref",
          "value": ""
        },
        "Sound": {
          "type": "resref",
          "value": ""
        },
        "Speaker": {
          "type": "cexostring",
          "value": ""
        },
        "Text": {
          "type": "cexolocstring",
          "value": {
            "0": "In an attempt to understand Avatars, Mages have attempted to classify them, coming up with four broad categories to describe the changes are brought to their Mages.  The Avatar Essence helps shape the Mage's Seekings, and determines how Resonance affects them."
          }
        }
      },
      {
        "__struct_id": 2,
        "Animation": {
          "type": "dword",
          "value": 0
        },
        "AnimLoop": {
          "type": "byte",
          "value": 1
        },
        "Comment": {
          "type": "cexostring",
          "value": ""
        },
        "Delay": {
          "type": "dword",
          "value": 4294967295
        },
        "Quest": {
          "type": "cexostring",
          "value": ""
        },
        "RepliesList": {
          "type": "list",
          "value": [
            {
              "__struct_id": 0,
              "Active": {
                "type": "resref",
                "value": ""
              },
              "Index": {
                "type": "dword",
                "value": 8
              },
              "IsChild": {
                "type": "byte",
                "value": 0
              }
            },
            {
              "__struct_id": 1,
              "Active": {
                "type": "resref",
                "value": ""
              },
              "Index": {
                "type": "dword",
                "value": 6
              },
              "IsChild": {
                "type": "byte",
                "value": 0
              }
            },
            {
              "__struct_id": 2,
              "Active": {
                "type": "resref",
                "value": ""
              },
              "Index": {
                "type": "dword",
                "value": 4
              },
              "IsChild": {
                "type": "byte",
                "value": 0
              }
            },
            {
              "__struct_id": 3,
              "Active": {
                "type": "resref",
                "value": ""
              },
              "Index": {
                "type": "dword",
                "value": 2
              },
              "IsChild": {
                "type": "byte",
                "value": 0
              }
            }
          ]
        },
        "Script": {
          "type": "resref",
          "value": ""
        },
        "Sound": {
          "type": "resref",
          "value": ""
        },
        "Speaker": {
          "type": "cexostring",
          "value": ""
        },
        "Text": {
          "type": "cexolocstring",
          "value": {
            "0": "Dynamic, Pattern, Primortial, and Questing."
          }
        }
      },
      {
        "__struct_id": 3,
        "Animation": {
          "type": "dword",
          "value": 0
        },
        "AnimLoop": {
          "type": "byte",
          "value": 1
        },
        "Comment": {
          "type": "cexostring",
          "value": ""
        },
        "Delay": {
          "type": "dword",
          "value": 4294967295
        },
        "Quest": {
          "type": "cexostring",
          "value": ""
        },
        "RepliesList": {
          "type": "list",
          "value": [
            {
              "__struct_id": 0,
              "Active": {
                "type": "resref",
                "value": ""
              },
              "Index": {
                "type": "dword",
                "value": 3
              },
              "IsChild": {
                "type": "byte",
                "value": 0
              }
            }
          ]
        },
        "Script": {
          "type": "resref",
          "value": ""
        },
        "Sound": {
          "type": "resref",
          "value": ""
        },
        "Speaker": {
          "type": "cexostring",
          "value": ""
        },
        "Text": {
          "type": "cexolocstring",
          "value": {
            "0": "A Questing Avatar glides over worn paths and crumbled ruins.  A questing soul, will lead a wizard on an endless journey past thickets of greed and snares of doubt.  Bearing gifts of balance, calm and vision, this spirit has more focus than the wild Dynamic and more imagination like the rigid Pattern.  Like the Primordial, he flows past obstacles, but his works are more temperate and beneficial."
          }
        }
      },
      {
        "__struct_id": 4,
        "Animation": {
          "type": "dword",
          "value": 0
        },
        "AnimLoop": {
          "type": "byte",
          "value": 1
        },
        "Comment": {
          "type": "cexostring",
          "value": ""
        },
        "Delay": {
          "type": "dword",
          "value": 4294967295
        },
        "Quest": {
          "type": "cexostring",
          "value": ""
        },
        "RepliesList": {
          "type": "list",
          "value": [
            {
              "__struct_id": 0,
              "Active": {
                "type": "resref",
                "value": ""
              },
              "Index": {
                "type": "dword",
                "value": 10
              },
              "IsChild": {
                "type": "byte",
                "value": 1
              },
              "LinkComment": {
                "type": "cexostring",
                "value": ""
              }
            }
          ]
        },
        "Script": {
          "type": "resref",
          "value": ""
        },
        "Sound": {
          "type": "resref",
          "value": ""
        },
        "Speaker": {
          "type": "cexostring",
          "value": ""
        },
        "Text": {
          "type": "cexolocstring",
          "value": {
            "0": "Indeed so.. These Avatars rarely take solid forms in dreams.  Like the winds they resemble, these spirits are formless, relentless and ephemeral.  Refreshing as they seem, such souls never rest.  Their Mages wander until death ends their journey. Their Essence Paradigm: Purpose comes from seeking and accomplishing goals.\n"
          }
        }
      },
      {
        "__struct_id": 5,
        "Animation": {
          "type": "dword",
          "value": 0
        },
        "AnimLoop": {
          "type": "byte",
          "value": 1
        },
        "Comment": {
          "type": "cexostring",
          "value": ""
        },
        "Delay": {
          "type": "dword",
          "value": 4294967295
        },
        "Quest": {
          "type": "cexostring",
          "value": ""
        },
        "RepliesList": {
          "type": "list",
          "value": [
            {
              "__struct_id": 0,
              "Active": {
                "type": "resref",
                "value": ""
              },
              "Index": {
                "type": "dword",
                "value": 5
              },
              "IsChild": {
                "type": "byte",
                "value": 0
              }
            }
          ]
        },
        "Script": {
          "type": "resref",
          "value": ""
        },
        "Sound": {
          "type": "resref",
          "value": ""
        },
        "Speaker": {
          "type": "cexostring",
          "value": ""
        },
        "Text": {
          "type": "cexolocstring",
          "value": {
            "0": "A Primordial Avatar keeps their silence, sweeping  their mage into their depths with seductive waves and currents.  Though their grace seems devil-sent, this urge is older than time and more hallowed than heaven.  The Avatar thrives on mysteries and carnal pleasures. Through a wild life, a Mage gives birth to a new world, and watches the old one from afar."
          }
        }
      },
      {
        "__struct_id": 6,
        "Animation": {
          "type": "dword",
          "value": 0
        },
        "AnimLoop": {
          "type": "byte",
          "value": 1
        },
        "Comment": {
          "type": "cexostring",
          "value": ""
        },
        "Delay": {
          "type": "dword",
          "value": 4294967295
        },
        "Quest": {
          "type": "cexostring",
          "value": ""
        },
        "RepliesList": {
          "type": "list",
          "value": [
            {
              "__struct_id": 0,
              "Active": {
                "type": "resref",
                "value": ""
              },
              "Index": {
                "type": "dword",
                "value": 10
              },
              "IsChild": {
                "type": "byte",
                "value": 1
              },
              "LinkComment": {
                "type": "cexostring",
                "value": ""
              }
            }
          ]
        },
        "Script": {
          "type": "resref",
          "value": ""
        },
        "Sound": {
          "type": "resref",
          "value": ""
        },
        "Speaker": {
          "type": "cexostring",
          "value": ""
        },
        "Text": {
          "type": "cexolocstring",
          "value": {
            "0": "A Primordial Avatar's  dreams often take the form of animals, Pagan gods and nature spirits.  The Mages they inspire have a knowing way about them and seem ancient, even if they're young. Their Essence Paradigm: The most basic things are the most powerful."
          }
        }
      },
      {
        "__struct_id": 7,
        "Animation": {
          "type": "dword",
          "value": 0
        },
        "AnimLoop": {
          "type": "byte",
          "value": 1
        },
        "Comment": {
          "type": "cexostring",
          "value": ""
        },
        "Delay": {
          "type": "dword",
          "value": 4294967295
        },
        "Quest": {
          "type": "cexostring",
          "value": ""
        },
        "RepliesList": {
          "type": "list",
          "value": [
            {
              "__struct_id": 0,
              "Active": {
                "type": "resref",
                "value": ""
              },
              "Index": {
                "type": "dword",
                "value": 7
              },
              "IsChild": {
                "type": "byte",
                "value": 0
              }
            }
          ]
        },
        "Script": {
          "type": "resref",
          "value": ""
        },
        "Sound": {
          "type": "resref",
          "value": ""
        },
        "Speaker": {
          "type": "cexostring",
          "value": ""
        },
        "Text": {
          "type": "cexolocstring",
          "value": {
            "0": "Pattern Avatasr safeguard the land, building wondrous things where chaos once reigned.  Comforting, ordered, and meticulous, he weaves webs of security.  Without his influence, Creation would spiral into madness.  This Avatar soothes pain, slays dragons and brings a wandering soul to peace."
          }
        }
      },
      {
        "__struct_id": 8,
        "Animation": {
          "type": "dword",
          "value": 0
        },
        "AnimLoop": {
          "type": "byte",
          "value": 1
        },
        "Comment": {
          "type": "cexostring",
          "value": ""
        },
        "Delay": {
          "type": "dword",
          "value": 4294967295
        },
        "Quest": {
          "type": "cexostring",
          "value": ""
        },
        "RepliesList": {
          "type": "list",
          "value": [
            {
              "__struct_id": 0,
              "Active": {
                "type": "resref",
                "value": ""
              },
              "Index": {
                "type": "dword",
                "value": 10
              },
              "IsChild": {
                "type": "byte",
                "value": 1
              },
              "LinkComment": {
                "type": "cexostring",
                "value": ""
              }
            }
          ]
        },
        "Script": {
          "type": "resref",
          "value": ""
        },
        "Sound": {
          "type": "resref",
          "value": ""
        },
        "Speaker": {
          "type": "cexostring",
          "value": ""
        },
        "Text": {
          "type": "cexolocstring",
          "value": {
            "0": "In a Mage's dreams, many Pattern Avatars appear as castles, parents, angels, and rays of light.  Although these Avatars work their Mages hard, the promise of order and comfort makes all sacrifices worthwhile. This Essence Paradigm: Strength comes from order and stability.\n"
          }
        }
      },
      {
        "__struct_id": 9,
        "Animation": {
          "type": "dword",
          "value": 0
        },
        "AnimLoop": {
          "type": "byte",
          "value": 1
        },
        "Comment": {
          "type": "cexostring",
          "value": ""
        },
        "Delay": {
          "type": "dword",
          "value": 4294967295
        },
        "Quest": {
          "type": "cexostring",
          "value": ""
        },
        "RepliesList": {
          "type": "list",
          "value": [
            {
              "__struct_id": 0,
              "Active": {
                "type": "resref",
                "value": ""
              },
              "Index": {
                "type": "dword",
                "value": 9
              },
              "IsChild": {
                "type": "byte",
                "value": 0
              }
            }
          ]
        },
        "Script": {
          "type": "resref",
          "value": ""
        },
        "Sound": {
          "type": "resref",
          "value": ""
        },
        "Speaker": {
          "type": "cexostring",
          "value": ""
        },
        "Text": {
          "type": "cexolocstring",
          "value": {
            "0": "A Dynamic Avatar tends to enjoy riding the flames of change, and will often drives a Mage to strive, alter, tear down and create. Restless and capricious, one will embody  the dynamic urge of chaos and wonder.  Taken to an extreme, this Essence can bring madness; more often, it tantalizes a Mage with the promise of novelty and the thrill of rebellion.\n"
          }
        }
      },
      {
        "__struct_id": 10,
        "Animation": {
          "type": "dword",
          "value": 0
        },
        "AnimLoop": {
          "type": "byte",
          "value": 1
        },
        "Comment": {
          "type": "cexostring",
          "value": ""
        },
        "Delay": {
          "type": "dword",
          "value": 4294967295
        },
        "Quest": {
          "type": "cexostring",
          "value": ""
        },
        "RepliesList": {
          "type": "list",
          "value": [
            {
              "__struct_id": 0,
              "Active": {
                "type": "resref",
                "value": ""
              },
              "Index": {
                "type": "dword",
                "value": 10
              },
              "IsChild": {
                "type": "byte",
                "value": 0
              }
            }
          ]
        },
        "Script": {
          "type": "resref",
          "value": ""
        },
        "Sound": {
          "type": "resref",
          "value": ""
        },
        "Speaker": {
          "type": "cexostring",
          "value": ""
        },
        "Text": {
          "type": "cexolocstring",
          "value": {
            "0": "The dreams a mage with a Dynamic Avatars often resemble pillars of flame, devils, whirlwinds and shadows.  Always hungry, ever-curious, they're brilliant, inspiring and often frightening to behold. This Essence Paradigm: Nothing is static, everything must change."
          }
        }
      }
    ]
  },
  "NumWords": {
    "type": "dword",
    "value": 504
  },
  "PreventZoomIn": {
    "type": "byte",
    "value": 0
  },
  "ReplyList": {
    "type": "list",
    "value": [
      {
        "__struct_id": 0,
        "Animation": {
          "type": "dword",
          "value": 0
        },
        "AnimLoop": {
          "type": "byte",
          "value": 1
        },
        "Comment": {
          "type": "cexostring",
          "value": ""
        },
        "Delay": {
          "type": "dword",
          "value": 4294967295
        },
        "EntriesList": {
          "type": "list",
          "value": [
            {
              "__struct_id": 0,
              "Active": {
                "type": "resref",
                "value": ""
              },
              "Index": {
                "type": "dword",
                "value": 1
              },
              "IsChild": {
                "type": "byte",
                "value": 0
              }
            }
          ]
        },
        "Quest": {
          "type": "cexostring",
          "value": ""
        },
        "Script": {
          "type": "resref",
          "value": ""
        },
        "Sound": {
          "type": "resref",
          "value": ""
        },
        "Text": {
          "type": "cexolocstring",
          "value": {
            "0": "Yes what can you tell me of them?"
          }
        }
      },
      {
        "__struct_id": 1,
        "Animation": {
          "type": "dword",
          "value": 0
        },
        "AnimLoop": {
          "type": "byte",
          "value": 1
        },
        "Comment": {
          "type": "cexostring",
          "value": ""
        },
        "Delay": {
          "type": "dword",
          "value": 4294967295
        },
        "EntriesList": {
          "type": "list",
          "value": [
            {
              "__struct_id": 0,
              "Active": {
                "type": "resref",
                "value": ""
              },
              "Index": {
                "type": "dword",
                "value": 2
              },
              "IsChild": {
                "type": "byte",
                "value": 0
              }
            }
          ]
        },
        "Quest": {
          "type": "cexostring",
          "value": ""
        },
        "Script": {
          "type": "resref",
          "value": ""
        },
        "Sound": {
          "type": "resref",
          "value": ""
        },
        "Text": {
          "type": "cexolocstring",
          "value": {
            "0": "What are those?"
          }
        }
      },
      {
        "__struct_id": 2,
        "Animation": {
          "type": "dword",
          "value": 0
        },
        "AnimLoop": {
          "type": "byte",
          "value": 1
        },
        "Comment": {
          "type": "cexostring",
          "value": ""
        },
        "Delay": {
          "type": "dword",
          "value": 4294967295
        },
        "EntriesList": {
          "type": "list",
          "value": [
            {
              "__struct_id": 0,
              "Active": {
                "type": "resref",
                "value": ""
              },
              "Index": {
                "type": "dword",
                "value": 3
              },
              "IsChild": {
                "type": "byte",
                "value": 0
              }
            }
          ]
        },
        "Quest": {
          "type": "cexostring",
          "value": ""
        },
        "Script": {
          "type": "resref",
          "value": ""
        },
        "Sound": {
          "type": "resref",
          "value": ""
        },
        "Text": {
          "type": "cexolocstring",
          "value": {
            "0": "Tell me more about Questing"
          }
        }
      },
      {
        "__struct_id": 3,
        "Animation": {
          "type": "dword",
          "value": 0
        },
        "AnimLoop": {
          "type": "byte",
          "value": 1
        },
        "Comment": {
          "type": "cexostring",
          "value": ""
        },
        "Delay": {
          "type": "dword",
          "value": 4294967295
        },
        "EntriesList": {
          "type": "list",
          "value": [
            {
              "__struct_id": 0,
              "Active": {
                "type": "resref",
                "value": ""
              },
              "Index": {
                "type": "dword",
                "value": 4
              },
              "IsChild": {
                "type": "byte",
                "value": 0
              }
            }
          ]
        },
        "Quest": {
          "type": "cexostring",
          "value": ""
        },
        "Script": {
          "type": "resref",
          "value": ""
        },
        "Sound": {
          "type": "resref",
          "value": ""
        },
        "Text": {
          "type": "cexolocstring",
          "value": {
            "0": "Seems stable enough"
          }
        }
      },
      {
        "__struct_id": 4,
        "Animation": {
          "type": "dword",
          "value": 0
        },
        "AnimLoop": {
          "type": "byte",
          "value": 1
        },
        "Comment": {
          "type": "cexostring",
          "value": ""
        },
        "Delay": {
          "type": "dword",
          "value": 4294967295
        },
        "EntriesList": {
          "type": "list",
          "value": [
            {
              "__struct_id": 0,
              "Active": {
                "type": "resref",
                "value": ""
              },
              "Index": {
                "type": "dword",
                "value": 5
              },
              "IsChild": {
                "type": "byte",
                "value": 0
              }
            }
          ]
        },
        "Quest": {
          "type": "cexostring",
          "value": ""
        },
        "Script": {
          "type": "resref",
          "value": ""
        },
        "Sound": {
          "type": "resref",
          "value": ""
        },
        "Text": {
          "type": "cexolocstring",
          "value": {
            "0": "Tell me more about Primortial"
          }
        }
      },
      {
        "__struct_id": 5,
        "Animation": {
          "type": "dword",
          "value": 0
        },
        "AnimLoop": {
          "type": "byte",
          "value": 1
        },
        "Comment": {
          "type": "cexostring",
          "value": ""
        },
        "Delay": {
          "type": "dword",
          "value": 4294967295
        },
        "EntriesList": {
          "type": "list",
          "value": [
            {
              "__struct_id": 0,
              "Active": {
                "type": "resref",
                "value": ""
              },
              "Index": {
                "type": "dword",
                "value": 6
              },
              "IsChild": {
                "type": "byte",
                "value": 0
              }
            }
          ]
        },
        "Quest": {
          "type": "cexostring",
          "value": ""
        },
        "Script": {
          "type": "resref",
          "value": ""
        },
        "Sound": {
          "type": "resref",
          "value": ""
        },
        "Text": {
          "type": "cexolocstring",
          "value": {
            "0": "Intense"
          }
        }
      },
      {
        "__struct_id": 6,
        "Animation": {
          "type": "dword",
          "value": 0
        },
        "AnimLoop": {
          "type": "byte",
          "value": 1
        },
        "Comment": {
          "type": "cexostring",
          "value": ""
        },
        "Delay": {
          "type": "dword",
          "value": 4294967295
        },
        "EntriesList": {
          "type": "list",
          "value": [
            {
              "__struct_id": 0,
              "Active": {
                "type": "resref",
                "value": ""
              },
              "Index": {
                "type": "dword",
                "value": 7
              },
              "IsChild": {
                "type": "byte",
                "value": 0
              }
            }
          ]
        },
        "Quest": {
          "type": "cexostring",
          "value": ""
        },
        "Script": {
          "type": "resref",
          "value": ""
        },
        "Sound": {
          "type": "resref",
          "value": ""
        },
        "Text": {
          "type": "cexolocstring",
          "value": {
            "0": "Tell me more about Pattern."
          }
        }
      },
      {
        "__struct_id": 7,
        "Animation": {
          "type": "dword",
          "value": 0
        },
        "AnimLoop": {
          "type": "byte",
          "value": 1
        },
        "Comment": {
          "type": "cexostring",
          "value": ""
        },
        "Delay": {
          "type": "dword",
          "value": 4294967295
        },
        "EntriesList": {
          "type": "list",
          "value": [
            {
              "__struct_id": 0,
              "Active": {
                "type": "resref",
                "value": ""
              },
              "Index": {
                "type": "dword",
                "value": 8
              },
              "IsChild": {
                "type": "byte",
                "value": 0
              }
            }
          ]
        },
        "Quest": {
          "type": "cexostring",
          "value": ""
        },
        "Script": {
          "type": "resref",
          "value": ""
        },
        "Sound": {
          "type": "resref",
          "value": ""
        },
        "Text": {
          "type": "cexolocstring",
          "value": {
            "0": "Bringing peace"
          }
        }
      },
      {
        "__struct_id": 8,
        "Animation": {
          "type": "dword",
          "value": 0
        },
        "AnimLoop": {
          "type": "byte",
          "value": 1
        },
        "Comment": {
          "type": "cexostring",
          "value": ""
        },
        "Delay": {
          "type": "dword",
          "value": 4294967295
        },
        "EntriesList": {
          "type": "list",
          "value": [
            {
              "__struct_id": 0,
              "Active": {
                "type": "resref",
                "value": ""
              },
              "Index": {
                "type": "dword",
                "value": 9
              },
              "IsChild": {
                "type": "byte",
                "value": 0
              }
            }
          ]
        },
        "Quest": {
          "type": "cexostring",
          "value": ""
        },
        "Script": {
          "type": "resref",
          "value": ""
        },
        "Sound": {
          "type": "resref",
          "value": ""
        },
        "Text": {
          "type": "cexolocstring",
          "value": {
            "0": "Tell me more about Dynamic"
          }
        }
      },
      {
        "__struct_id": 9,
        "Animation": {
          "type": "dword",
          "value": 0
        },
        "AnimLoop": {
          "type": "byte",
          "value": 1
        },
        "Comment": {
          "type": "cexostring",
          "value": ""
        },
        "Delay": {
          "type": "dword",
          "value": 4294967295
        },
        "EntriesList": {
          "type": "list",
          "value": [
            {
              "__struct_id": 0,
              "Active": {
                "type": "resref",
                "value": ""
              },
              "Index": {
                "type": "dword",
                "value": 10
              },
              "IsChild": {
                "type": "byte",
                "value": 0
              }
            }
          ]
        },
        "Quest": {
          "type": "cexostring",
          "value": ""
        },
        "Script": {
          "type": "resref",
          "value": ""
        },
        "Sound": {
          "type": "resref",
          "value": ""
        },
        "Text": {
          "type": "cexolocstring",
          "value": {
            "0": "Thrill of rebellion. . . "
          }
        }
      },
      {
        "__struct_id": 10,
        "Animation": {
          "type": "dword",
          "value": 0
        },
        "AnimLoop": {
          "type": "byte",
          "value": 1
        },
        "Comment": {
          "type": "cexostring",
          "value": ""
        },
        "Delay": {
          "type": "dword",
          "value": 4294967295
        },
        "EntriesList": {
          "type": "list",
          "value": [
            {
              "__struct_id": 0,
              "Active": {
                "type": "resref",
                "value": ""
              },
              "Index": {
                "type": "dword",
                "value": 2
              },
              "IsChild": {
                "type": "byte",
                "value": 1
              },
              "LinkComment": {
                "type": "cexostring",
                "value": ""
              }
            }
          ]
        },
        "Quest": {
          "type": "cexostring",
          "value": ""
        },
        "Script": {
          "type": "resref",
          "value": ""
        },
        "Sound": {
          "type": "resref",
          "value": ""
        },
        "Text": {
          "type": "cexolocstring",
          "value": {
            "0": "What more can I learn on others?"
          }
        }
      }
    ]
  },
  "StartingList": {
    "type": "list",
    "value": [
      {
        "__struct_id": 0,
        "Active": {
          "type": "resref",
          "value": ""
        },
        "Index": {
          "type": "dword",
          "value": 0
        }
      }
    ]
  }
}
